robotic_manipulator_rloa/__init__.py
robotic_manipulator_rloa/rl_framework.py
robotic_manipulator_rloa/environment/__init__.py
robotic_manipulator_rloa/environment/environment.py
robotic_manipulator_rloa/naf_components/__init__.py
robotic_manipulator_rloa/naf_components/naf_algorithm.py
robotic_manipulator_rloa/naf_components/naf_neural_network.py
robotic_manipulator_rloa/naf_components/demo_weights/__init__.py
robotic_manipulator_rloa/naf_components/demo_weights/weights_kuka.p
robotic_manipulator_rloa/naf_components/demo_weights/weights_xarm6.p
robotic_manipulator_rloa/utils/__init__.py
robotic_manipulator_rloa/utils/collision_detector.py
robotic_manipulator_rloa/utils/exceptions.py
robotic_manipulator_rloa/utils/logger.py
robotic_manipulator_rloa/utils/replay_buffer.py
robotic_manipulator_rloa-1.0.0.dist-info/LICENSE
robotic_manipulator_rloa-1.0.0.dist-info/METADATA
robotic_manipulator_rloa-1.0.0.dist-info/WHEEL
robotic_manipulator_rloa-1.0.0.dist-info/top_level.txt
robotic_manipulator_rloa-1.0.0.dist-info/RECORD
