Metadata-Version: 2.1
Name: robotic-manipulator-rloa
Version: 1.0.0
Summary: Framework for training Robotic Manipulators on the Obstacle Avoidance task through Reinforcement Learning.
Author-email: Javier Martinez <jmartinezojeda5upv@gmail.com>
License: MIT License
Project-URL: Homepage, https://github.com/JavierMtz5/robotic_manipulator_rloa
Project-URL: Repository, https://github.com/JavierMtz5/robotic_manipulator_rloa
Project-URL: Documentation, https://javiermtz5.github.io/robotic_manipulator_rloa/
Keywords: Robotics,Manipulator,Framework,Reinforcement Learning,Obstacle Avoidance
Classifier: License :: OSI Approved :: MIT License
Classifier: Programming Language :: Python
Classifier: Programming Language :: Python :: 3
Classifier: Operating System :: Microsoft :: Windows
Classifier: Operating System :: POSIX :: Linux
Classifier: Framework :: Robot Framework
Requires-Python: >=3.8
License-File: LICENSE
Requires-Dist: torch
Requires-Dist: numpy
Requires-Dist: pybullet
Requires-Dist: matplotlib
